vassure_ai-1.0.9.data/data/docs/readme/README.html
vassure_ai-1.0.9.data/data/docs/readme/README.jpeg
vassure_ai-1.0.9.data/data/docs/readme/README.md
vassure_ai-1.0.9.data/data/docs/readme/README.pdf
vassure_ai-1.0.9.data/data/docs/readme/README.png
vassure_ai-1.0.9.data/data/docs/technical/technicalguide.html
vassure_ai-1.0.9.data/data/docs/technical/technicalguide.jpeg
vassure_ai-1.0.9.data/data/docs/technical/technicalguide.md
vassure_ai-1.0.9.data/data/docs/technical/technicalguide.pdf
vassure_ai-1.0.9.data/data/docs/technical/technicalguide.png
vassure_ai-1.0.9.data/data/docs/user/userguide.html
vassure_ai-1.0.9.data/data/docs/user/userguide.jpeg
vassure_ai-1.0.9.data/data/docs/user/userguide.md
vassure_ai-1.0.9.data/data/docs/user/userguide.pdf
vassure_ai-1.0.9.data/data/docs/user/userguide.png
vassureai/README.html
vassureai/README.jpeg
vassureai/README.md
vassureai/README.pdf
vassureai/README.png
vassureai/__init__.py
vassureai/cli.py
vassureai/conftest.py
vassureai/core.py
vassureai/create_pdf.py
vassureai/pytest.ini
vassureai/metrics/__init__.py
vassureai/metrics/load_tester.py
vassureai/metrics/metrics_reporter.py
vassureai/metrics/monitoring.py
vassureai/metrics/metrics_data/create_deviation_20250426_221550.json
vassureai/metrics/metrics_data/execution_summary_20250426_221551.json
vassureai/metrics/metrics_data/execution_summary_20250426_221815.json
vassureai/metrics/metrics_data/sample_testcase_20250426_221814.json
vassureai/tests/__init__.py
vassureai/tests/conftest.py
vassureai/tests/test_create_deviation.py
vassureai/tests/__pycache__/test_create_deviation.cpython-311-pytest-8.3.5.pyc.11880
vassureai/tests/__pycache__/test_sample_testcase.cpython-311-pytest-8.3.5.pyc.16944
vassureai/userguide/userguide.html
vassureai/userguide/userguide.jpeg
vassureai/userguide/userguide.md
vassureai/userguide/userguide.pdf
vassureai/userguide/userguide.png
vassureai/utils/__init__.py
vassureai/utils/base_test.py
vassureai/utils/config.py
vassure_ai-1.0.9.dist-info/METADATA
vassure_ai-1.0.9.dist-info/WHEEL
vassure_ai-1.0.9.dist-info/entry_points.txt
vassure_ai-1.0.9.dist-info/top_level.txt
vassure_ai-1.0.9.dist-info/RECORD
